easy_geotool/__init__.py
easy_geotool/main.py
easy_geotool/utils.py
easy_geotool/io/__init__.py
easy_geotool/io/raster.py
easy_geotool/io/vector.py
easy_geotool/raster/__init__.py
easy_geotool/raster/display.py
easy_geotool/raster/process.py
easy_geotool/transform/__init__.py
easy_geotool/transform/transform copy.py
easy_geotool/transform/transform.py
easy_geotool/vector/__init__.py
easy_geotool/vector/display.py
easy_geotool/vector/process.py
easy_geotool-0.1.2.dist-info/LICENSE
easy_geotool-0.1.2.dist-info/METADATA
easy_geotool-0.1.2.dist-info/WHEEL
easy_geotool-0.1.2.dist-info/top_level.txt
easy_geotool-0.1.2.dist-info/RECORD
